general_operator/__init__.py
general_operator/app/__init__.py
general_operator/app/SQL/__init__.py
general_operator/app/SQL/database.py
general_operator/app/SQL/sql_operate.py
general_operator/app/influxdb/__init__.py
general_operator/app/influxdb/influxdb.py
general_operator/app/influxdb/influxdb_operate.py
general_operator/app/redis_db/__init__.py
general_operator/app/redis_db/function.py
general_operator/app/redis_db/redis_db.py
general_operator/app/redis_db/redis_operate.py
general_operator/dependencies/__init__.py
general_operator/dependencies/db_dependencies.py
general_operator/dependencies/get_query_dependencies.py
general_operator/function/General_operate.py
general_operator/function/__init__.py
general_operator/function/all_table.py
general_operator/function/create_data_structure.py
general_operator/function/encoder.py
general_operator/function/exception.py
general_operator/function/search_function.py
general_operator/routers/General_table_router.py
general_operator/routers/__init__.py
general_operator/routers/all_table.py
general_operator-0.4.6.dist-info/METADATA
general_operator-0.4.6.dist-info/WHEEL
general_operator-0.4.6.dist-info/top_level.txt
general_operator-0.4.6.dist-info/RECORD
