Metadata-Version: 2.1
Name: general_operator
Version: 0.4.6
Summary: general operator for fastapi write sql and redis
Home-page: https://github.com/littlebluewhite/node_object_module
Author: wilson
Author-email: wwilson008@gmail.com
Classifier: Development Status :: 3 - Alpha
Classifier: Intended Audience :: Developers
Classifier: Topic :: Software Development :: Build Tools
Classifier: License :: OSI Approved :: MIT License
Classifier: Programming Language :: Python :: 3
Classifier: Programming Language :: Python :: 3.8
Classifier: Programming Language :: Python :: 3.9
Classifier: Programming Language :: Python :: 3.10
Classifier: Programming Language :: Python :: 3.11
Classifier: Programming Language :: Python :: 3.12
Requires-Python: >=3.8
Requires-Dist: fastapi >=0.83.0
Requires-Dist: influxdb-client >=1.22.0
Requires-Dist: redis >=5.0.1
Requires-Dist: SQLAlchemy >=2.0.10
